funcinputs/__init__.py
funcinputs-1.1.2.dist-info/LICENSE.txt
funcinputs-1.1.2.dist-info/METADATA
funcinputs-1.1.2.dist-info/WHEEL
funcinputs-1.1.2.dist-info/top_level.txt
funcinputs-1.1.2.dist-info/RECORD
