Metadata-Version: 2.1
Name: funcinputs
Version: 1.1.2
Summary: inputs for functions
Author-email: Johannes <johannes-programming@mailfence.com>
License: The MIT License (MIT)
Project-URL: Documentation, https://pypi.org/project/funcinputs
Project-URL: Download, https://pypi.org/project/funcinputs/#files
Project-URL: Source, https://github.com/johannes-programming/funcinputs
Classifier: License :: OSI Approved :: MIT License
Classifier: Programming Language :: Python
Classifier: Programming Language :: Python :: 3
Classifier: Programming Language :: Python :: 3 :: Only
Requires-Python: >=3.11
License-File: LICENSE.txt
